<Quimica>
	<Elemento>
		<Nombre>Hidrógeno</Nombre>
		<Simbolo>H</Simbolo>
		<Estado>Gas</Estado>
		<NAtomico>1</NAtomico>
	</Elemento>
	<Elemento>
		<Nombre>Helio</Nombre>
		<Simbolo>He</Simbolo>
		<Estado>Gas</Estado>
		<NAtomico>2</NAtomico>
	</Elemento>
	<Elemento>
		<Nombre>Litio</Nombre>
		<Simbolo>Li</Simbolo>
		<Estado>Sólido</Estado>
		<NAtomico>3</NAtomico>
	</Elemento>
	<Elemento>
		<Nombre>Berilio</Nombre>
		<Simbolo>Be</Simbolo>
		<Estado>Sólido</Estado>
		<NAtomico>4</NAtomico>
	</Elemento>
	<Elemento>
		<Nombre>Boro</Nombre>
		<Simbolo>B</Simbolo>
		<Estado>Líquido</Estado>
		<NAtomico>5</NAtomico>
	</Elemento>
	<Elemento>
		<Nombre>Carbono</Nombre>
		<Simbolo>C</Simbolo>
		<Estado>Sólido</Estado>
		<NAtomico>6</NAtomico>
	</Elemento>
	<Elemento>
		<Nombre>Nitrógeno</Nombre>
		<Simbolo>N</Simbolo>
		<Estado>Gas</Estado>
		<NAtomico>7</NAtomico>
	</Elemento>
	<Elemento>
		<Nombre>Oxígeno</Nombre>
		<Simbolo>O</Simbolo>
		<Estado>Gas</Estado>
		<NAtomico>8</NAtomico>
	</Elemento>
	<Elemento>
		<Nombre>Flúor</Nombre>
		<Simbolo>F</Simbolo>
		<Estado>Gas</Estado>
		<NAtomico>9</NAtomico>
	</Elemento>
	<Elemento>
		<Nombre>Neón</Nombre>
		<Simbolo>Ne</Simbolo>
		<Estado>Gas</Estado>
		<NAtomico>10</NAtomico>
	</Elemento>
	<Elemento>
		<Nombre>Sodio</Nombre>
		<Simbolo>Na</Simbolo>
		<Estado>Sólido</Estado>
		<NAtomico>11</NAtomico>
	</Elemento>
	<Elemento>
		<Nombre>Magnesio</Nombre>
		<Simbolo>Mg</Simbolo>
		<Estado>Sólido</Estado>
		<NAtomico>12</NAtomico>
	</Elemento>
	<Elemento>
		<Nombre>Aluminio</Nombre>
		<Simbolo>Al</Simbolo>
		<Estado>Sólido</Estado>
		<NAtomico>13</NAtomico>
	</Elemento>
	<Elemento>
		<Nombre>Silicio</Nombre>
		<Simbolo>Si</Simbolo>
		<Estado>Sólido</Estado>
		<NAtomico>14</NAtomico>
	</Elemento>
	<Elemento>
		<Nombre>Fósforo</Nombre>
		<Simbolo>P</Simbolo>
		<Estado>Sólido</Estado>
		<NAtomico>15</NAtomico>
	</Elemento>
	<Elemento>
		<Nombre>Azufre</Nombre>
		<Simbolo>S</Simbolo>
		<Estado>Sólido</Estado>
		<NAtomico>16</NAtomico>
	</Elemento>
	<Elemento>
		<Nombre>Cloro</Nombre>
		<Simbolo>Cl</Simbolo>
		<Estado>Gas</Estado>
		<NAtomico>17</NAtomico>
	</Elemento>
	<Elemento>
		<Nombre>Argón</Nombre>
		<Simbolo>Ar</Simbolo>
		<Estado>Gas</Estado>
		<NAtomico>18</NAtomico>
	</Elemento>
	<Elemento>
		<Nombre>Potasio</Nombre>
		<Simbolo>K</Simbolo>
		<Estado>Sólido</Estado>
		<NAtomico>19</NAtomico>
	</Elemento>
	<Elemento>
		<Nombre>Calcio</Nombre>
		<Simbolo>Ca</Simbolo>
		<Estado>Sólido</Estado>
		<NAtomico>20</NAtomico>
	</Elemento>
	<Elemento>
		<Nombre>Escandio</Nombre>
		<Simbolo>Sc</Simbolo>
		<Estado>Sólido</Estado>
		<NAtomico>21</NAtomico>
	</Elemento>
	<Elemento>
		<Nombre>Titanio</Nombre>
		<Simbolo>Ti</Simbolo>
		<Estado>Sólido</Estado>
		<NAtomico>22</NAtomico>
	</Elemento>
	<Elemento>
		<Nombre>Vanadio</Nombre>
		<Simbolo>V</Simbolo>
		<Estado>Sólido</Estado>
		<NAtomico>23</NAtomico>
	</Elemento>
	<Elemento>
		<Nombre>Cromo</Nombre>
		<Simbolo>Cr</Simbolo>
		<Estado>Sólido</Estado>
		<NAtomico>24</NAtomico>
	</Elemento>
	<Elemento>
		<Nombre>Manganeso</Nombre>
		<Simbolo>Mn</Simbolo>
		<Estado>Sólido</Estado>
		<NAtomico>25</NAtomico>
	</Elemento>
	<Elemento>
		<Nombre>Hierro</Nombre>
		<Simbolo>Fe</Simbolo>
		<Estado>Sólido</Estado>
		<NAtomico>26</NAtomico>
	</Elemento>
	<Elemento>
		<Nombre>Cobalto</Nombre>
		<Simbolo>Co</Simbolo>
		<Estado>Sólido</Estado>
		<NAtomico>27</NAtomico>
	</Elemento>
	<Elemento>
		<Nombre>Níquel</Nombre>
		<Simbolo>Ni</Simbolo>
		<Estado>Sólido</Estado>
		<NAtomico>28</NAtomico>
	</Elemento>
	<Elemento>
		<Nombre>Cobre</Nombre>
		<Simbolo>Cu</Simbolo>
		<Estado>Sólido</Estado>
		<NAtomico>29</NAtomico>
	</Elemento>
	<Elemento>
		<Nombre>Zinc</Nombre>
		<Simbolo>Zn</Simbolo>
		<Estado>Sólido</Estado>
		<NAtomico>30</NAtomico>
	</Elemento>
	<Elemento>
		<Nombre>Galio</Nombre>
		<Simbolo>Ga</Simbolo>
		<Estado>Sólido</Estado>
		<NAtomico>31</NAtomico>
	</Elemento>
	<Elemento>
		<Nombre>Germanio</Nombre>
		<Simbolo>Ge</Simbolo>
		<Estado>Sólido</Estado>
		<NAtomico>32</NAtomico>
	</Elemento>
	<Elemento>
		<Nombre>Arsénico</Nombre>
		<Simbolo>As</Simbolo>
		<Estado>Sólido</Estado>
		<NAtomico>33</NAtomico>
	</Elemento>
	<Elemento>
		<Nombre>Selenio</Nombre>
		<Simbolo>Se</Simbolo>
		<Estado>Sólido</Estado>
		<NAtomico>34</NAtomico>
	</Elemento>
	<Elemento>
		<Nombre>Bromo</Nombre>
		<Simbolo>Br</Simbolo>
		<Estado>Líquido</Estado>
		<NAtomico>35</NAtomico>
	</Elemento>
	<Elemento>
		<Nombre>Criptón</Nombre>
		<Simbolo>Kr</Simbolo>
		<Estado>Gas</Estado>
		<NAtomico>36</NAtomico>
	</Elemento>
	<Elemento>
		<Nombre>Rubidio</Nombre>
		<Simbolo>Rb</Simbolo>
		<Estado>Sólido</Estado>
		<NAtomico>37</NAtomico>
	</Elemento>
	<Elemento>
		<Nombre>Estroncio</Nombre>
		<Simbolo>Sr</Simbolo>
		<Estado>Sólido</Estado>
		<NAtomico>38</NAtomico>
	</Elemento>
	<Elemento>
		<Nombre>Itrio</Nombre>
		<Simbolo>Y</Simbolo>
		<Estado>Sólido</Estado>
		<NAtomico>39</NAtomico>
	</Elemento>
	<Elemento>
		<Nombre>Zirconio</Nombre>
		<Simbolo>Zr</Simbolo>
		<Estado>Sólido</Estado>
		<NAtomico>40</NAtomico>
	</Elemento>
	<Elemento>
		<Nombre>Niobio</Nombre>
		<Simbolo>Nb</Simbolo>
		<Estado>Sólido</Estado>
		<NAtomico>41</NAtomico>
	</Elemento>
	<Elemento>
		<Nombre>Molibdeno</Nombre>
		<Simbolo>Mo</Simbolo>
		<Estado>Sólido</Estado>
		<NAtomico>42</NAtomico>
	</Elemento>
	<Elemento>
		<Nombre>Tecnecio</Nombre>
		<Simbolo>Tc</Simbolo>
		<Estado>Sólido</Estado>
		<NAtomico>43</NAtomico>
	</Elemento>
	<Elemento>
		<Nombre>Rutenio</Nombre>
		<Simbolo>Ru</Simbolo>
		<Estado>Sólido</Estado>
		<NAtomico>44</NAtomico>
	</Elemento>
	<Elemento>
		<Nombre>Rodio</Nombre>
		<Simbolo>Rh</Simbolo>
		<Estado>Sólido</Estado>
		<NAtomico>45</NAtomico>
	</Elemento>
	<Elemento>
		<Nombre>Paladio</Nombre>
		<Simbolo>Pd</Simbolo>
		<Estado>Sólido</Estado>
		<NAtomico>46</NAtomico>
	</Elemento>
	<Elemento>
		<Nombre>Plata</Nombre>
		<Simbolo>Ag</Simbolo>
		<Estado>Sólido</Estado>
		<NAtomico>47</NAtomico>
	</Elemento>
	<Elemento>
		<Nombre>Cadmio</Nombre>
		<Simbolo>Cd</Simbolo>
		<Estado>Sólido</Estado>
		<NAtomico>48</NAtomico>
	</Elemento>
	<Elemento>
		<Nombre>Indio</Nombre>
		<Simbolo>In</Simbolo>
		<Estado>Sólido</Estado>
		<NAtomico>49</NAtomico>
	</Elemento>
	<Elemento>
		<Nombre>Estaño</Nombre>
		<Simbolo>Sn</Simbolo>
		<Estado>Sólido</Estado>
		<NAtomico>50</NAtomico>
	</Elemento>
	<Elemento>
		<Nombre>Antimonio</Nombre>
		<Simbolo>Sb</Simbolo>
		<Estado>Sólido</Estado>
		<NAtomico>51</NAtomico>
	</Elemento>
	<Elemento>
		<Nombre>Teluro</Nombre>
		<Simbolo>Te</Simbolo>
		<Estado>Sólido</Estado>
		<NAtomico>52</NAtomico>
	</Elemento>
	<Elemento>
		<Nombre>Yodo</Nombre>
		<Simbolo>I</Simbolo>
		<Estado>Sólido</Estado>
		<NAtomico>53</NAtomico>
	</Elemento>
	<Elemento>
		<Nombre>Xenón</Nombre>
		<Simbolo>Xe</Simbolo>
		<Estado>Gas</Estado>
		<NAtomico>54</NAtomico>
	</Elemento>
	<Elemento>
		<Nombre>Cesio</Nombre>
		<Simbolo>Cs</Simbolo>
		<Estado>Sólido</Estado>
		<NAtomico>55</NAtomico>
	</Elemento>
	<Elemento>
		<Nombre>Bario</Nombre>
		<Simbolo>Ba</Simbolo>
		<Estado>Sólido</Estado>
		<NAtomico>56</NAtomico>
	</Elemento>
	<Elemento>
		<Nombre>Lantano</Nombre>
		<Simbolo>La</Simbolo>
		<Estado>Sólido</Estado>
		<NAtomico>57</NAtomico>
	</Elemento>
	<Elemento>
		<Nombre>Hafnio</Nombre>
		<Simbolo>Hf</Simbolo>
		<Estado>Sólido</Estado>
		<NAtomico>72</NAtomico>
	</Elemento>
	<Elemento>
		<Nombre>Tántalo</Nombre>
		<Simbolo>Ta</Simbolo>
		<Estado>Sólido</Estado>
		<NAtomico>73</NAtomico>
	</Elemento>
	<Elemento>
		<Nombre>Tungsteno</Nombre>
		<Simbolo>W</Simbolo>
		<Estado>Sólido</Estado>
		<NAtomico>74</NAtomico>
	</Elemento>
	<Elemento>
		<Nombre>Renio</Nombre>
		<Simbolo>Re</Simbolo>
		<Estado>Sólido</Estado>
		<NAtomico>75</NAtomico>
	</Elemento>
	<Elemento>
		<Nombre>Osmio</Nombre>
		<Simbolo>Os</Simbolo>
		<Estado>Sólido</Estado>
		<NAtomico>76</NAtomico>
	</Elemento>
	<Elemento>
		<Nombre>Iridio</Nombre>
		<Simbolo>Ir</Simbolo>
		<Estado>Sólido</Estado>
		<NAtomico>77</NAtomico>
	</Elemento>
	<Elemento>
		<Nombre>Platino</Nombre>
		<Simbolo>Pt</Simbolo>
		<Estado>Sólido</Estado>
		<NAtomico>78</NAtomico>
	</Elemento>
	<Elemento>
		<Nombre>Oro</Nombre>
		<Simbolo>Au</Simbolo>
		<Estado>Sólido</Estado>
		<NAtomico>79</NAtomico>
	</Elemento>
	<Elemento>
		<Nombre>Mercurio</Nombre>
		<Simbolo>Hg</Simbolo>
		<Estado>Líquido</Estado>
		<NAtomico>80</NAtomico>
	</Elemento>
	<Elemento>
		<Nombre>Talio</Nombre>
		<Simbolo>Tl</Simbolo>
		<Estado>Sólido</Estado>
		<NAtomico>81</NAtomico>
	</Elemento>
	<Elemento>
		<Nombre>Plomo</Nombre>
		<Simbolo>Pb</Simbolo>
		<Estado>Sólido</Estado>
		<NAtomico>82</NAtomico>
	</Elemento>
	<Elemento>
		<Nombre>Bismuto</Nombre>
		<Simbolo>Bi</Simbolo>
		<Estado>Sólido</Estado>
		<NAtomico>83</NAtomico>
	</Elemento>
	<Elemento>
		<Nombre>Polonio</Nombre>
		<Simbolo>Po</Simbolo>
		<Estado>Sólido</Estado>
		<NAtomico>84</NAtomico>
	</Elemento>
	<Elemento>
		<Nombre>Astato</Nombre>
		<Simbolo>At</Simbolo>
		<Estado>Sólido</Estado>
		<NAtomico>85</NAtomico>
	</Elemento>
	<Elemento>
		<Nombre>Radón</Nombre>
		<Simbolo>Rn</Simbolo>
		<Estado>Gas</Estado>
		<NAtomico>86</NAtomico>
	</Elemento>
	<Elemento>
		<Nombre>Francio</Nombre>
		<Simbolo>Fr</Simbolo>
		<Estado>Sólido</Estado>
		<NAtomico>87</NAtomico>
	</Elemento>
	<Elemento>
		<Nombre>Radio</Nombre>
		<Simbolo>Ra</Simbolo>
		<Estado>Sólido</Estado>
		<NAtomico>88</NAtomico>
	</Elemento>
	<Elemento>
		<Nombre>Actinio</Nombre>
		<Simbolo>Ac</Simbolo>
		<Estado>Sólido</Estado>
		<NAtomico>89</NAtomico>
	</Elemento>
	<Elemento>
		<Nombre>Torio</Nombre>
		<Simbolo>Th</Simbolo>
		<Estado>Sólido</Estado>
		<NAtomico>90</NAtomico>
	</Elemento>
</Quimica>
